forest_fire_clustering/__init__.py
forest_fire_clustering/forest_fire_clustering.py
forest_fire_clustering-0.0.25.dist-info/LICENSE.md
forest_fire_clustering-0.0.25.dist-info/METADATA
forest_fire_clustering-0.0.25.dist-info/WHEEL
forest_fire_clustering-0.0.25.dist-info/top_level.txt
forest_fire_clustering-0.0.25.dist-info/RECORD
