Metadata-Version: 2.1
Name: forest_fire_clustering
Version: 0.0.25
Summary: Clustering method based on Forest Fire Dynamics
Home-page: https://github.com/flynn-chen/forest-fire-clustering
Author: Flynn Chen
Author-email: flynn.chen@yale.edu
License: UNKNOWN
Project-URL: Bug Tracker, https://github.com/flynn-chen/forest-fire-clustering/issues
Platform: UNKNOWN
Classifier: Programming Language :: Python :: 3
Classifier: License :: OSI Approved :: MIT License
Classifier: Operating System :: OS Independent
Requires-Python: >=3.6
License-File: LICENSE.md
